CHANGES.txt
MANIFEST.in
README.txt
bootstrap.py
buildout.cfg
setup.py
tox.ini
src/z3c/__init__.py
src/z3c.sampledata.egg-info/PKG-INFO
src/z3c.sampledata.egg-info/SOURCES.txt
src/z3c.sampledata.egg-info/dependency_links.txt
src/z3c.sampledata.egg-info/namespace_packages.txt
src/z3c.sampledata.egg-info/not-zip-safe
src/z3c.sampledata.egg-info/requires.txt
src/z3c.sampledata.egg-info/top_level.txt
src/z3c/sampledata/README.txt
src/z3c/sampledata/TODO.txt
src/z3c/sampledata/__init__.py
src/z3c/sampledata/configure.zcml
src/z3c/sampledata/data.py
src/z3c/sampledata/ftesting.zcml
src/z3c/sampledata/ftests.py
src/z3c/sampledata/interfaces.py
src/z3c/sampledata/layer.py
src/z3c/sampledata/manager.py
src/z3c/sampledata/meta.zcml
src/z3c/sampledata/metaconfigure.py
src/z3c/sampledata/metadirectives.py
src/z3c/sampledata/testlines.csv
src/z3c/sampledata/testlines.txt
src/z3c/sampledata/tests.py
src/z3c/sampledata/browser/README.txt
src/z3c/sampledata/browser/__init__.py
src/z3c/sampledata/browser/configure.zcml
src/z3c/sampledata/browser/generate.pt
src/z3c/sampledata/browser/managers.pt
src/z3c/sampledata/browser/testmanager.zcml
src/z3c/sampledata/browser/views.py
src/z3c/sampledata/generator/__init__.py
src/z3c/sampledata/generator/configure.zcml
src/z3c/sampledata/generator/intids.py
src/z3c/sampledata/generator/intids.txt
src/z3c/sampledata/generator/pau.py
src/z3c/sampledata/generator/pau.txt
src/z3c/sampledata/generator/principals.py
src/z3c/sampledata/generator/principals.txt
src/z3c/sampledata/generator/site.py
src/z3c/sampledata/generator/site.txt