Metadata-Version: 1.1
Name: z3c.sampledata
Version: 1.0.0
Summary: Sampledata Generator
Home-page: http://pypi.python.org/pypi/z3c.sampledata
Author: Stephan Richter and the Zope Community
Author-email: zope-dev@zope.org
License: ZPL 2.1
Keywords: zope3 z3c sampledata
Platform: UNKNOWN
Classifier: Development Status :: 5 - Production/Stable
Classifier: Environment :: Web Environment
Classifier: Intended Audience :: Developers
Classifier: License :: OSI Approved :: Zope Public License
Classifier: Programming Language :: Python
Classifier: Programming Language :: Python :: 2
Classifier: Programming Language :: Python :: 2.6
Classifier: Programming Language :: Python :: 2.7
Classifier: Programming Language :: Python :: Implementation :: CPython
Classifier: Natural Language :: English
Classifier: Operating System :: OS Independent
Classifier: Topic :: Internet :: WWW/HTTP
Classifier: Framework :: Zope3
